<annotation>
    <folder>VOC2007</folder>
    <filename>IMG_8398.png</filename>
    <size>
        <width>3024</width>
        <height>3024</height>
        <depth>3</depth>
    </size>
    <object>
        <name>groove</name>
        <pose>Unspecified</pose>
        <truncated>0</truncated>
        <difficult>0</difficult>
        <bndbox>
            <xmin>1413</xmin>
            <ymin>1139</ymin>
            <xmax>1473</xmax>
            <ymax>1204</ymax>
        </bndbox>
    </object>
    <object>
        <name>groove</name>
        <pose>Unspecified</pose>
        <truncated>0</truncated>
        <difficult>0</difficult>
        <bndbox>
            <xmin>1625</xmin>
            <ymin>1820</ymin>
            <xmax>1706</xmax>
            <ymax>1889</ymax>
        </bndbox>
    </object>
</annotation>