<annotation>
    <folder>VOC2007</folder>
    <filename>IMG_8828.png</filename>
    <size>
        <width>3024</width>
        <height>3024</height>
        <depth>3</depth>
    </size>
    <object>
        <name>ablation</name>
        <pose>Unspecified</pose>
        <truncated>0</truncated>
        <difficult>0</difficult>
        <bndbox>
            <xmin>923</xmin>
            <ymin>640</ymin>
            <xmax>1626</xmax>
            <ymax>1343</ymax>
        </bndbox>
    </object>
</annotation>