<annotation>
    <folder>VOC2007</folder>
    <filename>IMG_8204.png</filename>
    <size>
        <width>3024</width>
        <height>3024</height>
        <depth>3</depth>
    </size>
    <object>
        <name>groove</name>
        <pose>Unspecified</pose>
        <truncated>0</truncated>
        <difficult>0</difficult>
        <bndbox>
            <xmin>1523</xmin>
            <ymin>2424</ymin>
            <xmax>1576</xmax>
            <ymax>2480</ymax>
        </bndbox>
    </object>
    <object>
        <name>groove</name>
        <pose>Unspecified</pose>
        <truncated>0</truncated>
        <difficult>0</difficult>
        <bndbox>
            <xmin>1876</xmin>
            <ymin>2689</ymin>
            <xmax>1929</xmax>
            <ymax>2736</ymax>
        </bndbox>
    </object>
    <object>
        <name>groove</name>
        <pose>Unspecified</pose>
        <truncated>0</truncated>
        <difficult>0</difficult>
        <bndbox>
            <xmin>1491</xmin>
            <ymin>2829</ymin>
            <xmax>1523</xmax>
            <ymax>2886</ymax>
        </bndbox>
    </object>
</annotation>