<annotation>
    <folder>VOC2007</folder>
    <filename>IMG_8879(1).png</filename>
    <size>
        <width>2210</width>
        <height>2264</height>
        <depth>3</depth>
    </size>
    <object>
        <name>ablation</name>
        <pose>Unspecified</pose>
        <truncated>0</truncated>
        <difficult>0</difficult>
        <bndbox>
            <xmin>679</xmin>
            <ymin>584</ymin>
            <xmax>1025</xmax>
            <ymax>989</ymax>
        </bndbox>
    </object>
</annotation>