<annotation>
    <folder>VOC2007</folder>
    <filename>IMG_8212(1).png</filename>
    <size>
        <width>2310</width>
        <height>1917</height>
        <depth>3</depth>
    </size>
    <object>
        <name>groove</name>
        <pose>Unspecified</pose>
        <truncated>0</truncated>
        <difficult>0</difficult>
        <bndbox>
            <xmin>602</xmin>
            <ymin>232</ymin>
            <xmax>654</xmax>
            <ymax>270</ymax>
        </bndbox>
    </object>
    <object>
        <name>groove</name>
        <pose>Unspecified</pose>
        <truncated>0</truncated>
        <difficult>0</difficult>
        <bndbox>
            <xmin>1096</xmin>
            <ymin>536</ymin>
            <xmax>1154</xmax>
            <ymax>586</ymax>
        </bndbox>
    </object>
    <object>
        <name>groove</name>
        <pose>Unspecified</pose>
        <truncated>0</truncated>
        <difficult>0</difficult>
        <bndbox>
            <xmin>614</xmin>
            <ymin>822</ymin>
            <xmax>670</xmax>
            <ymax>862</ymax>
        </bndbox>
    </object>
</annotation>